timminfo.py
timm_info-0.1.0.dist-info/LICENSE
timm_info-0.1.0.dist-info/METADATA
timm_info-0.1.0.dist-info/WHEEL
timm_info-0.1.0.dist-info/entry_points.txt
timm_info-0.1.0.dist-info/top_level.txt
timm_info-0.1.0.dist-info/RECORD
